YehuoIMxLinuxKaifaShizhanZhinanFix1/README.md
YehuoIMxLinuxKaifaShizhanZhinanFix1/__init__.py
YehuoIMxLinuxKaifaShizhanZhinanFix1/__main__.py
YehuoIMxLinuxKaifaShizhanZhinanFix1/file.epub
YehuoIMxLinuxKaifaShizhanZhinanFix1/index.html
YehuoIMxLinuxKaifaShizhanZhinanFix1/css/__init__.py
YehuoIMxLinuxKaifaShizhanZhinanFix1/css/annotations.css
YehuoIMxLinuxKaifaShizhanZhinanFix1/css/main.css
YehuoIMxLinuxKaifaShizhanZhinanFix1/css/normalize.css
YehuoIMxLinuxKaifaShizhanZhinanFix1/css/popup.css
YehuoIMxLinuxKaifaShizhanZhinanFix1/font/__init__.py
YehuoIMxLinuxKaifaShizhanZhinanFix1/font/fontello.eot
YehuoIMxLinuxKaifaShizhanZhinanFix1/font/fontello.svg
YehuoIMxLinuxKaifaShizhanZhinanFix1/font/fontello.ttf
YehuoIMxLinuxKaifaShizhanZhinanFix1/font/fontello.woff
YehuoIMxLinuxKaifaShizhanZhinanFix1/img/__init__.py
YehuoIMxLinuxKaifaShizhanZhinanFix1/img/annotator-glyph-sprite.png
YehuoIMxLinuxKaifaShizhanZhinanFix1/img/annotator-icon-sprite.png
YehuoIMxLinuxKaifaShizhanZhinanFix1/img/apple-touch-icon.png
YehuoIMxLinuxKaifaShizhanZhinanFix1/img/cancelfullscreen.png
YehuoIMxLinuxKaifaShizhanZhinanFix1/img/close.png
YehuoIMxLinuxKaifaShizhanZhinanFix1/img/fullscreen.png
YehuoIMxLinuxKaifaShizhanZhinanFix1/img/loader.gif
YehuoIMxLinuxKaifaShizhanZhinanFix1/img/menu-icon.png
YehuoIMxLinuxKaifaShizhanZhinanFix1/img/save.png
YehuoIMxLinuxKaifaShizhanZhinanFix1/img/saved.png
YehuoIMxLinuxKaifaShizhanZhinanFix1/img/settings-s.png
YehuoIMxLinuxKaifaShizhanZhinanFix1/img/settings.png
YehuoIMxLinuxKaifaShizhanZhinanFix1/img/star.png
YehuoIMxLinuxKaifaShizhanZhinanFix1/js/__init__.py
YehuoIMxLinuxKaifaShizhanZhinanFix1/js/epub.js
YehuoIMxLinuxKaifaShizhanZhinanFix1/js/epub.min.js
YehuoIMxLinuxKaifaShizhanZhinanFix1/js/epub.min.map
YehuoIMxLinuxKaifaShizhanZhinanFix1/js/hooks.min.js
YehuoIMxLinuxKaifaShizhanZhinanFix1/js/hooks.min.map
YehuoIMxLinuxKaifaShizhanZhinanFix1/js/reader.js
YehuoIMxLinuxKaifaShizhanZhinanFix1/js/reader.js.map
YehuoIMxLinuxKaifaShizhanZhinanFix1/js/reader.min.js
yehuo_i_mx_linux_kaifa_shizhan_zhinan_fix1-2025.3.24.0.dist-info/METADATA
yehuo_i_mx_linux_kaifa_shizhan_zhinan_fix1-2025.3.24.0.dist-info/WHEEL
yehuo_i_mx_linux_kaifa_shizhan_zhinan_fix1-2025.3.24.0.dist-info/entry_points.txt
yehuo_i_mx_linux_kaifa_shizhan_zhinan_fix1-2025.3.24.0.dist-info/top_level.txt
yehuo_i_mx_linux_kaifa_shizhan_zhinan_fix1-2025.3.24.0.dist-info/RECORD
